{
	"1": {
		"ParaName": "淫欲",
		"Idea": "",
		"Variable": 1021,
		"DspType": "Open",
		"flavor01": "拥有正直的心，身体对污秽之事一无所知。",
		"flavor02": "虽然拥有着正直的心，但也逐渐了解到了性的快乐。",
		"flavor03": "心正在染上淫秽的色彩。",
		"flavor04": "沉溺于作为雌性的快乐，每晚都忍受着疯狂的饥渴感。",
		"flavor05": "身体已经沉醉于快感，理性正在被侵蚀。"
	},
	"2": {
		"ParaName": "侵蚀度",
		"Idea": "",
		"Variable": 1022,
		"DspType": "Open",
		"flavor01": "",
		"flavor02": "",
		"flavor03": "",
		"flavor04": "",
		"flavor05": ""
	},
	"3": {
		"ParaName": "学校评价",
		"Idea": "种子",
		"Variable": 1023,
		"DspType": "Close",
		"flavor01": "",
		"flavor02": "",
		"flavor03": "",
		"flavor04": "",
		"flavor05": ""
	},
	"4": {
		"ParaName": "声誉",
		"Idea": "",
		"Variable": 1024,
		"DspType": "Open",
		"flavor01": "",
		"flavor02": "",
		"flavor03": "",
		"flavor04": "",
		"flavor05": ""
	},
	"5": {
		"ParaName": "知名度",
		"Idea": "",
		"Variable": 1025,
		"DspType": "Open",
		"flavor01": "",
		"flavor02": "",
		"flavor03": "",
		"flavor04": "",
		"flavor05": ""
	},
	"6": {
		"ParaName": "快感值",
		"Idea": "",
		"Variable": 1026,
		"DspType": "Open",
		"flavor01": "",
		"flavor02": "",
		"flavor03": "",
		"flavor04": "",
		"flavor05": ""
	},
	"7": {
		"ParaName": "发情值",
		"Idea": "",
		"Variable": 1027,
		"DspType": "Open",
		"flavor01": "",
		"flavor02": "",
		"flavor03": "",
		"flavor04": "",
		"flavor05": ""
	},
	"8": {
		"ParaName": "最大发情值",
		"Idea": "",
		"Variable": 1028,
		"DspType": "Open",
		"flavor01": "",
		"flavor02": "",
		"flavor03": "",
		"flavor04": "",
		"flavor05": ""
	},
	"9": {
		"ParaName": "战意",
		"Idea": "活性最大",
		"Variable": 1029,
		"DspType": "Close",
		"flavor01": "",
		"flavor02": "",
		"flavor03": "",
		"flavor04": "",
		"flavor05": ""
	},
	"10": {
		"ParaName": "瘴气汚染值",
		"Idea": "",
		"Variable": 1030,
		"DspType": "Open",
		"flavor01": "",
		"flavor02": "",
		"flavor03": "",
		"flavor04": "",
		"flavor05": ""
	},
	"11": {
		"ParaName": "最大快感值",
		"Idea": "",
		"Variable": 1031,
		"DspType": "Open",
		"flavor01": "",
		"flavor02": "",
		"flavor03": "",
		"flavor04": "",
		"flavor05": ""
	},
	"12": {
		"ParaName": "穿衣状态？",
		"Idea": "",
		"Variable": 1032,
		"DspType": "Open",
		"flavor01": "",
		"flavor02": "",
		"flavor03": "",
		"flavor04": "",
		"flavor05": ""
	},
	"13": {
		"ParaName": "淫乱级别",
		"Idea": "",
		"Variable": 1033,
		"DspType": "Open",
		"flavor01": "",
		"flavor02": "",
		"flavor03": "",
		"flavor04": "",
		"flavor05": ""
	},
	"14": {
		"ParaName": "n\/a",
		"Idea": "",
		"Variable": 1034,
		"DspType": "Close",
		"flavor01": "??????",
		"flavor02": "",
		"flavor03": "",
		"flavor04": "",
		"flavor05": ""
	},
	"15": {
		"ParaName": "n\/a",
		"Idea": "炮友的人数？",
		"Variable": 1035,
		"DspType": "Close",
		"flavor01": "??????",
		"flavor02": "",
		"flavor03": "",
		"flavor04": "",
		"flavor05": ""
	},
	"16": {
		"ParaName": "n\/a",
		"Idea": "主人的人数？",
		"Variable": 1036,
		"DspType": "Close",
		"flavor01": "??????",
		"flavor02": "",
		"flavor03": "",
		"flavor04": "",
		"flavor05": ""
	},
	"17": {
		"ParaName": "n\/a",
		"Idea": "",
		"Variable": 1037,
		"DspType": "Close",
		"flavor01": "??????",
		"flavor02": "",
		"flavor03": "",
		"flavor04": "",
		"flavor05": ""
	},
	"18": {
		"ParaName": "B",
		"Idea": "",
		"Variable": 1038,
		"DspType": "Open",
		"flavor01": "92",
		"flavor02": "92",
		"flavor03": "92",
		"flavor04": "92",
		"flavor05": "92"
	},
	"19": {
		"ParaName": "H",
		"Idea": "",
		"Variable": 1039,
		"DspType": "Open",
		"flavor01": "65",
		"flavor02": "65",
		"flavor03": "65",
		"flavor04": "65",
		"flavor05": "65"
	},
	"20": {
		"ParaName": "W",
		"Idea": "",
		"Variable": 1040,
		"DspType": "Open",
		"flavor01": "89",
		"flavor02": "89",
		"flavor03": "89",
		"flavor04": "89",
		"flavor05": "89"
	},
	"21": {
		"ParaName": "爱抚经验",
		"Idea": "",
		"Variable": 1041,
		"DspType": "Open",
		"flavor01": "没有接触过异性的纯洁身体。",
		"flavor02": "",
		"flavor03": "",
		"flavor04": "",
		"flavor05": ""
	},
	"22": {
		"ParaName": "接吻经验",
		"Idea": "",
		"Variable": 1042,
		"DspType": "Open",
		"flavor01": "还不知道接吻滋味的嘴唇。",
		"flavor02": "",
		"flavor03": "",
		"flavor04": "",
		"flavor05": ""
	},
	"23": {
		"ParaName": "自慰经验",
		"Idea": "",
		"Variable": 1043,
		"DspType": "Open",
		"flavor01": "几乎没有做过。",
		"flavor02": "有时身体渴望的时候会一个人做。",
		"flavor03": "",
		"flavor04": "",
		"flavor05": ""
	},
	"24": {
		"ParaName": "n\/a",
		"Idea": "",
		"Variable": 1044,
		"DspType": "Open",
		"flavor01": "??????",
		"flavor02": "",
		"flavor03": "",
		"flavor04": "",
		"flavor05": ""
	},
	"25": {
		"ParaName": "性爱经验",
		"Idea": "",
		"Variable": 1045,
		"DspType": "Open",
		"flavor01": "完全没有经验的处女。",
		"flavor02": "",
		"flavor03": "",
		"flavor04": "",
		"flavor05": ""
	},
	"26": {
		"ParaName": "A.性爱经验",
		"Idea": "",
		"Variable": 1046,
		"DspType": "Open",
		"flavor01": "只知道本来的用途。",
		"flavor02": "",
		"flavor03": "",
		"flavor04": "",
		"flavor05": ""
	},
	"27": {
		"ParaName": "n\/a",
		"Idea": "",
		"Variable": 1047,
		"DspType": "Close",
		"flavor01": "??????",
		"flavor02": "",
		"flavor03": "",
		"flavor04": "",
		"flavor05": ""
	},
	"28": {
		"ParaName": "n\/a",
		"Idea": "",
		"Variable": 1048,
		"DspType": "Close",
		"flavor01": "??????",
		"flavor02": "",
		"flavor03": "",
		"flavor04": "",
		"flavor05": ""
	},
	"29": {
		"ParaName": "n\/a",
		"Idea": "",
		"Variable": 1049,
		"DspType": "Close",
		"flavor01": "??????",
		"flavor02": "",
		"flavor03": "",
		"flavor04": "",
		"flavor05": ""
	},
	"30": {
		"ParaName": "n\/a",
		"Idea": "",
		"Variable": 1050,
		"DspType": "Close",
		"flavor01": "??????",
		"flavor02": "",
		"flavor03": "",
		"flavor04": "",
		"flavor05": ""
	},
	"31": {
		"ParaName": "侍奉经验",
		"Idea": "",
		"Variable": 1051,
		"DspType": "Open",
		"flavor01": "??????",
		"flavor02": "",
		"flavor03": "",
		"flavor04": "",
		"flavor05": ""
	},
	"32": {
		"ParaName": "n\/a",
		"Idea": "",
		"Variable": 1052,
		"DspType": "Close",
		"flavor01": "??????",
		"flavor02": "",
		"flavor03": "",
		"flavor04": "",
		"flavor05": "身体上的任何部位都能为雄性服务。"
	},
	"33": {
		"ParaName": "内射经验",
		"Idea": "",
		"Variable": 1053,
		"DspType": "Close",
		"flavor01": "??????",
		"flavor02": "",
		"flavor03": "",
		"flavor04": "",
		"flavor05": ""
	},
	"34": {
		"ParaName": "精浴经验",
		"Idea": "",
		"Variable": 1054,
		"DspType": "Close",
		"flavor01": "??????",
		"flavor02": "",
		"flavor03": "",
		"flavor04": "",
		"flavor05": ""
	},
	"35": {
		"ParaName": "精饮经验",
		"Idea": "",
		"Variable": 1055,
		"DspType": "Close",
		"flavor01": "??????",
		"flavor02": "",
		"flavor03": "",
		"flavor04": "",
		"flavor05": ""
	},
	"36": {
		"ParaName": "肛射经验",
		"Idea": "",
		"Variable": 1056,
		"DspType": "Close",
		"flavor01": "??????",
		"flavor02": "",
		"flavor03": "",
		"flavor04": "",
		"flavor05": ""
	},
	"37": {
		"ParaName": "高潮经验",
		"Idea": "",
		"Variable": 1057,
		"DspType": "Open",
		"flavor01": "还不知道高潮是什么。",
		"flavor02": "已经体验过高潮。",
		"flavor03": "",
		"flavor04": "",
		"flavor05": ""
	},
	"38": {
		"ParaName": "n\/a",
		"Idea": "",
		"Variable": 1058,
		"DspType": "Close",
		"flavor01": "??????",
		"flavor02": "",
		"flavor03": "",
		"flavor04": "",
		"flavor05": ""
	},
	"39": {
		"ParaName": "n\/a",
		"Idea": "",
		"Variable": 1059,
		"DspType": "Close",
		"flavor01": "??????",
		"flavor02": "",
		"flavor03": "",
		"flavor04": "",
		"flavor05": ""
	},
	"40": {
		"ParaName": "n\/a",
		"Idea": "",
		"Variable": 1060,
		"DspType": "Close",
		"flavor01": "??????",
		"flavor02": "",
		"flavor03": "",
		"flavor04": "",
		"flavor05": ""
	},
	"41": {
		"ParaName": "凌辱经验",
		"Idea": "",
		"Variable": 1061,
		"DspType": "Close",
		"flavor01": "??????",
		"flavor02": "",
		"flavor03": "",
		"flavor04": "",
		"flavor05": ""
	},
	"42": {
		"ParaName": "羞耻经验",
		"Idea": "",
		"Variable": 1062,
		"DspType": "Close",
		"flavor01": "??????",
		"flavor02": "曾经被别人看见过害羞的样子。",
		"flavor03": "",
		"flavor04": "",
		"flavor05": ""
	},
	"43": {
		"ParaName": "痴汉经验",
		"Idea": "",
		"Variable": 1063,
		"DspType": "Close",
		"flavor01": "??????",
		"flavor02": "",
		"flavor03": "",
		"flavor04": "",
		"flavor05": ""
	},
	"44": {
		"ParaName": "摄影经验",
		"Idea": "",
		"Variable": 1064,
		"DspType": "Close",
		"flavor01": "??????",
		"flavor02": "",
		"flavor03": "",
		"flavor04": "",
		"flavor05": ""
	},
	"45": {
		"ParaName": "轮奸经验",
		"Idea": "",
		"Variable": 1065,
		"DspType": "Close",
		"flavor01": "??????",
		"flavor02": "",
		"flavor03": "",
		"flavor04": "",
		"flavor05": ""
	},
	"46": {
		"ParaName": "便器经验",
		"Idea": "",
		"Variable": 1066,
		"DspType": "Close",
		"flavor01": "??????",
		"flavor02": "",
		"flavor03": "",
		"flavor04": "",
		"flavor05": ""
	},
	"47": {
		"ParaName": "催眠经验",
		"Idea": "",
		"Variable": 1067,
		"DspType": "Close",
		"flavor01": "??????",
		"flavor02": "",
		"flavor03": "",
		"flavor04": "",
		"flavor05": ""
	},
	"48": {
		"ParaName": "n\/a",
		"Idea": "",
		"Variable": 1068,
		"DspType": "Close",
		"flavor01": "??????",
		"flavor02": "",
		"flavor03": "",
		"flavor04": "",
		"flavor05": ""
	},
	"49": {
		"ParaName": "卖春经验",
		"Idea": "",
		"Variable": 1069,
		"DspType": "Close",
		"flavor01": "??????",
		"flavor02": "",
		"flavor03": "",
		"flavor04": "",
		"flavor05": ""
	},
	"50": {
		"ParaName": "战败凌辱经验",
		"Idea": "",
		"Variable": 1070,
		"DspType": "Close",
		"flavor01": "??????",
		"flavor02": "",
		"flavor03": "",
		"flavor04": "",
		"flavor05": ""
	},
	"51": {
		"ParaName": "战败监禁经验",
		"Idea": "",
		"Variable": 1071,
		"DspType": "Close",
		"flavor01": "??????",
		"flavor02": "",
		"flavor03": "",
		"flavor04": "",
		"flavor05": ""
	},
	"52": {
		"ParaName": "妊娠经验",
		"Idea": "",
		"Variable": 1072,
		"DspType": "Close",
		"flavor01": "??????",
		"flavor02": "",
		"flavor03": "",
		"flavor04": "",
		"flavor05": ""
	},
	"53": {
		"ParaName": "n\/a",
		"Idea": "",
		"Variable": 1073,
		"DspType": "Close",
		"flavor01": "??????",
		"flavor02": "",
		"flavor03": "",
		"flavor04": "",
		"flavor05": ""
	},
	"54": {
		"ParaName": "妊娠天数",
		"Idea": "",
		"Variable": 1074,
		"DspType": "Close",
		"flavor01": "??????",
		"flavor02": "",
		"flavor03": "",
		"flavor04": "",
		"flavor05": ""
	},
	"55": {
		"ParaName": "诅咒经验",
		"Idea": "",
		"Variable": 1075,
		"DspType": "Close",
		"flavor01": "??????",
		"flavor02": "",
		"flavor03": "",
		"flavor04": "",
		"flavor05": ""
	},
	"56": {
		"ParaName": "被虐经验",
		"Idea": "",
		"Variable": 1076,
		"DspType": "Close",
		"flavor01": "??????",
		"flavor02": "",
		"flavor03": "",
		"flavor04": "",
		"flavor05": ""
	},
	"57": {
		"ParaName": "n\/a",
		"Idea": "",
		"Variable": 1077,
		"DspType": "Close",
		"flavor01": "??????",
		"flavor02": "",
		"flavor03": "",
		"flavor04": "",
		"flavor05": ""
	},
	"58": {
		"ParaName": "公開凌辱经验",
		"Idea": "",
		"Variable": 1078,
		"DspType": "Close",
		"flavor01": "??????",
		"flavor02": "",
		"flavor03": "",
		"flavor04": "",
		"flavor05": ""
	},
	"59": {
		"ParaName": "n\/a",
		"Idea": "",
		"Variable": 1079,
		"DspType": "Close",
		"flavor01": "??????",
		"flavor02": "",
		"flavor03": "",
		"flavor04": "",
		"flavor05": ""
	},
	"60": {
		"ParaName": "连续高潮记录",
		"Idea": "",
		"Variable": 1080,
		"DspType": "Close",
		"flavor01": "??????",
		"flavor02": "",
		"flavor03": "",
		"flavor04": "",
		"flavor05": ""
	},
	"61": {
		"ParaName": "学校淫行经验",
		"Idea": "",
		"Variable": 1175,
		"DspType": "Close",
		"flavor01": "??????",
		"flavor02": "",
		"flavor03": "",
		"flavor04": "",
		"flavor05": ""
	},
	"62": {
		"ParaName": "n\/a",
		"Idea": "",
		"Variable": 0,
		"DspType": "",
		"flavor01": "",
		"flavor02": "",
		"flavor03": "",
		"flavor04": "",
		"flavor05": ""
	},
	"63": {
		"ParaName": "n\/a",
		"Idea": "",
		"Variable": 0,
		"DspType": "",
		"flavor01": "",
		"flavor02": "",
		"flavor03": "",
		"flavor04": "",
		"flavor05": ""
	},
	"64": {
		"ParaName": "n\/a",
		"Idea": "",
		"Variable": 0,
		"DspType": "",
		"flavor01": "",
		"flavor02": "",
		"flavor03": "",
		"flavor04": "",
		"flavor05": ""
	},
	"65": {
		"ParaName": "n\/a",
		"Idea": "",
		"Variable": 1141,
		"DspType": "Close",
		"flavor01": "",
		"flavor02": "",
		"flavor03": "",
		"flavor04": "",
		"flavor05": ""
	},
	"66": {
		"ParaName": "按摩经验",
		"Idea": "",
		"Variable": 1142,
		"DspType": "Close",
		"flavor01": "",
		"flavor02": "",
		"flavor03": "",
		"flavor04": "",
		"flavor05": ""
	},
	"67": {
		"ParaName": "n\/a",
		"Idea": "",
		"Variable": 1143,
		"DspType": "Close",
		"flavor01": "",
		"flavor02": "",
		"flavor03": "",
		"flavor04": "",
		"flavor05": ""
	},
	"68": {
		"ParaName": "n\/a",
		"Idea": "",
		"Variable": 1144,
		"DspType": "Close",
		"flavor01": "",
		"flavor02": "",
		"flavor03": "",
		"flavor04": "",
		"flavor05": ""
	},
	"69": {
		"ParaName": "n\/a",
		"Idea": "",
		"Variable": 1145,
		"DspType": "Close",
		"flavor01": "",
		"flavor02": "",
		"flavor03": "",
		"flavor04": "",
		"flavor05": ""
	},
	"70": {
		"ParaName": "n\/a",
		"Idea": "",
		"Variable": 1146,
		"DspType": "Close",
		"flavor01": "",
		"flavor02": "",
		"flavor03": "",
		"flavor04": "",
		"flavor05": ""
	},
	"71": {
		"ParaName": "n\/a",
		"Idea": "",
		"Variable": 1147,
		"DspType": "Close",
		"flavor01": "",
		"flavor02": "",
		"flavor03": "",
		"flavor04": "",
		"flavor05": ""
	},
	"72": {
		"ParaName": "n\/a",
		"Idea": "",
		"Variable": 1148,
		"DspType": "Close",
		"flavor01": "",
		"flavor02": "",
		"flavor03": "",
		"flavor04": "",
		"flavor05": ""
	},
	"73": {
		"ParaName": "露出经验",
		"Idea": "",
		"Variable": 1149,
		"DspType": "Close",
		"flavor01": "",
		"flavor02": "",
		"flavor03": "",
		"flavor04": "",
		"flavor05": ""
	},
	"74": {
		"ParaName": "色情经验",
		"Idea": "",
		"Variable": 1150,
		"DspType": "Close",
		"flavor01": "",
		"flavor02": "",
		"flavor03": "",
		"flavor04": "",
		"flavor05": ""
	},
	"75": {
		"ParaName": "n\/a",
		"Idea": "",
		"Variable": 1151,
		"DspType": "Close",
		"flavor01": "",
		"flavor02": "",
		"flavor03": "",
		"flavor04": "",
		"flavor05": ""
	},
	"76": {
		"ParaName": "性骚扰经验",
		"Idea": "",
		"Variable": 1152,
		"DspType": "Close",
		"flavor01": "",
		"flavor02": "",
		"flavor03": "",
		"flavor04": "",
		"flavor05": ""
	},
	"77": {
		"ParaName": "n\/a",
		"Idea": "",
		"Variable": 1153,
		"DspType": "Close",
		"flavor01": "",
		"flavor02": "",
		"flavor03": "",
		"flavor04": "",
		"flavor05": ""
	},
	"78": {
		"ParaName": "n\/a",
		"Idea": "",
		"Variable": 1154,
		"DspType": "Close",
		"flavor01": "",
		"flavor02": "",
		"flavor03": "",
		"flavor04": "",
		"flavor05": ""
	},
	"79": {
		"ParaName": "n\/a",
		"Idea": "",
		"Variable": 1155,
		"DspType": "Close",
		"flavor01": "",
		"flavor02": "",
		"flavor03": "",
		"flavor04": "",
		"flavor05": ""
	},
	"80": {
		"ParaName": "触手经验",
		"Idea": "",
		"Variable": 1156,
		"DspType": "Close",
		"flavor01": "",
		"flavor02": "",
		"flavor03": "",
		"flavor04": "",
		"flavor05": ""
	},
	"81": {
		"ParaName": "n\/a",
		"Idea": "",
		"Variable": 1157,
		"DspType": "Close",
		"flavor01": "",
		"flavor02": "",
		"flavor03": "",
		"flavor04": "",
		"flavor05": ""
	},
	"82": {
		"ParaName": "药物经验",
		"Idea": "",
		"Variable": 1158,
		"DspType": "Close",
		"flavor01": "",
		"flavor02": "",
		"flavor03": "",
		"flavor04": "",
		"flavor05": ""
	},
	"83": {
		"ParaName": "单次最高快感",
		"Idea": "",
		"Variable": 1159,
		"DspType": "Close",
		"flavor01": "",
		"flavor02": "",
		"flavor03": "",
		"flavor04": "",
		"flavor05": ""
	},
	"84": {
		"ParaName": "n\/a",
		"Idea": "",
		"Variable": 1160,
		"DspType": "Close",
		"flavor01": "",
		"flavor02": "",
		"flavor03": "",
		"flavor04": "",
		"flavor05": ""
	},
	"85": {
		"ParaName": "n\/a",
		"Idea": "",
		"Variable": 1161,
		"DspType": "Close",
		"flavor01": "",
		"flavor02": "",
		"flavor03": "",
		"flavor04": "",
		"flavor05": ""
	},
	"86": {
		"ParaName": "n\/a",
		"Idea": "",
		"Variable": 1162,
		"DspType": "Close",
		"flavor01": "",
		"flavor02": "",
		"flavor03": "",
		"flavor04": "",
		"flavor05": ""
	},
	"87": {
		"ParaName": "n\/a",
		"Idea": "",
		"Variable": 1163,
		"DspType": "Close",
		"flavor01": "",
		"flavor02": "",
		"flavor03": "",
		"flavor04": "",
		"flavor05": ""
	},
	"88": {
		"ParaName": "n\/a",
		"Idea": "",
		"Variable": 1164,
		"DspType": "Close",
		"flavor01": "",
		"flavor02": "",
		"flavor03": "",
		"flavor04": "",
		"flavor05": ""
	},
	"89": {
		"ParaName": "n\/a",
		"Idea": "",
		"Variable": 1165,
		"DspType": "Close",
		"flavor01": "",
		"flavor02": "",
		"flavor03": "",
		"flavor04": "",
		"flavor05": ""
	},
	"90": {
		"ParaName": "n\/a",
		"Idea": "",
		"Variable": 1166,
		"DspType": "Close",
		"flavor01": "",
		"flavor02": "",
		"flavor03": "",
		"flavor04": "",
		"flavor05": ""
	},
	"91": {
		"ParaName": "n\/a",
		"Idea": "",
		"Variable": 1167,
		"DspType": "Close",
		"flavor01": "",
		"flavor02": "",
		"flavor03": "",
		"flavor04": "",
		"flavor05": ""
	},
	"92": {
		"ParaName": "n\/a",
		"Idea": "",
		"Variable": 1168,
		"DspType": "Close",
		"flavor01": "",
		"flavor02": "",
		"flavor03": "",
		"flavor04": "",
		"flavor05": ""
	},
	"93": {
		"ParaName": "n\/a",
		"Idea": "",
		"Variable": 1169,
		"DspType": "Close",
		"flavor01": "",
		"flavor02": "",
		"flavor03": "",
		"flavor04": "",
		"flavor05": ""
	},
	"94": {
		"ParaName": "n\/a",
		"Idea": "",
		"Variable": 1170,
		"DspType": "Close",
		"flavor01": "",
		"flavor02": "",
		"flavor03": "",
		"flavor04": "",
		"flavor05": ""
	},
	"95": {
		"ParaName": "n\/a",
		"Idea": "",
		"Variable": 1171,
		"DspType": "Close",
		"flavor01": "",
		"flavor02": "",
		"flavor03": "",
		"flavor04": "",
		"flavor05": ""
	},
	"96": {
		"ParaName": "n\/a",
		"Idea": "",
		"Variable": 1172,
		"DspType": "Close",
		"flavor01": "",
		"flavor02": "",
		"flavor03": "",
		"flavor04": "",
		"flavor05": ""
	},
	"97": {
		"ParaName": "n\/a",
		"Idea": "",
		"Variable": 1173,
		"DspType": "Close",
		"flavor01": "",
		"flavor02": "",
		"flavor03": "",
		"flavor04": "",
		"flavor05": ""
	},
	"98": {
		"ParaName": "n\/a",
		"Idea": "",
		"Variable": 1174,
		"DspType": "Close",
		"flavor01": "",
		"flavor02": "",
		"flavor03": "",
		"flavor04": "",
		"flavor05": ""
	},
	"99": {
		"ParaName": "",
		"Idea": "",
		"Variable": 0,
		"DspType": "",
		"flavor01": "",
		"flavor02": "",
		"flavor03": "",
		"flavor04": "",
		"flavor05": ""
	}
}